kmhook/__init__.py
kmhook/_kmhook_other.py
kmhook/_kmhook_win.py
kmhook-1.0.2.dist-info/METADATA
kmhook-1.0.2.dist-info/WHEEL
kmhook-1.0.2.dist-info/top_level.txt
kmhook-1.0.2.dist-info/RECORD
