Metadata-Version: 2.1
Name: kmhook
Version: 1.0.2
Summary: Fiddle with mouse and french keyboard under Windows
Author-email: Frédéric Leleu <ugli@mailo.com>
License: MIT License
Project-URL: Homepage, https://github.com/UGL1/kmhook
Keywords: keyboard,mouse,detect,event,synthesize,press,release,move
Classifier: Programming Language :: Python :: 3
Requires-Python: >=3.10
